scottbrian_utils/__init__.py
scottbrian_utils/__init__.pyi
scottbrian_utils/diag_msg.py
scottbrian_utils/doc_checker.py
scottbrian_utils/entry_trace.py
scottbrian_utils/exc_hook.py
scottbrian_utils/file_catalog.py
scottbrian_utils/flower_box.py
scottbrian_utils/log_verifier.py
scottbrian_utils/msgs.py
scottbrian_utils/pauser.py
scottbrian_utils/py.typed
scottbrian_utils/stop_watch.py
scottbrian_utils/testlib_verifier.py
scottbrian_utils/time_hdr.py
scottbrian_utils/timer.py
scottbrian_utils/unique_ts.py
scottbrian_utils-6.0.0.dist-info/licenses/LICENSE
scottbrian_utils-6.0.0.dist-info/METADATA
scottbrian_utils-6.0.0.dist-info/WHEEL
scottbrian_utils-6.0.0.dist-info/top_level.txt
scottbrian_utils-6.0.0.dist-info/RECORD
