Metadata-Version: 2.4
Name: scottbrian_utils
Version: 6.0.0
Summary: Miscellaneous utilities
Author-email: Scott Tuttle <sbtuttle@outlook.com>
License-Expression: MIT
Project-URL: Documentation, https://scottbrian-utils.readthedocs.io/en/latest/
Project-URL: Source, https://github.com/ScottBrian/scottbrian_utils.git
Keywords: utilities
Classifier: Development Status :: 5 - Production/Stable
Classifier: Intended Audience :: Developers
Classifier: Topic :: Software Development :: Libraries :: Python Modules
Classifier: Topic :: System :: Recovery Tools
Classifier: Topic :: Utilities
Classifier: Programming Language :: Python :: 3
Classifier: Programming Language :: Python :: 3.12
Classifier: Programming Language :: Python :: 3.13
Classifier: Operating System :: Microsoft :: Windows :: Windows 11
Requires-Python: ~=3.13
License-File: LICENSE
Requires-Dist: more-itertools~=10.8
Requires-Dist: pandas~=2.3
Requires-Dist: typing_extensions~=4.15
Requires-Dist: wrapt~=1.17
Dynamic: license-file
